{
    "company_email": "hello@weelabs.io",
    "company_name": "WeeLabs",
    "redis_expire": 604800,
    "session_length_in_seconds": 86400,
    "password_reset": {
        "allowed_time_to_complete_in_seconds": 86400,
        "allowed_time_between_requests_in_seconds": 60
    },
    "constants": {
        "seconds": {
            "five_minutes": 300,
            "one_hour": 3600,
            "one_week": 604800,
            "twenty_four_hours": 86400
        },
        "ms": {
            "five_minutes": 300000,
            "one_hour": 3600000,
            "one_week": 604800000,
            "twenty_four_hours": 86400000
        }
    }
}
